i18nx/__init__.py
i18nx-1.3.0.dist-info/LICENSE
i18nx-1.3.0.dist-info/METADATA
i18nx-1.3.0.dist-info/WHEEL
i18nx-1.3.0.dist-info/top_level.txt
i18nx-1.3.0.dist-info/RECORD
