Metadata-Version: 2.1
Name: i18nx
Version: 1.3.0
Summary: Lightweight i18n for Python
Home-page: https://gitlab.com/demsking/i18nx
Author: Sébastien Demanou
Author-email: demsking@gmail.com
License: MIT
Project-URL: Documentation, https://gitlab.com/demsking/i18nx/-/blob/main/README.md
Project-URL: Say Thanks!, https://www.buymeacoffee.com/demsking
Project-URL: Source, https://gitlab.com/demsking/i18nx
Project-URL: Tracker, https://gitlab.com/demsking/i18nx/-/issues
Keywords: i18n internationalization translate
Classifier: Development Status :: 5 - Production/Stable
Classifier: Intended Audience :: Developers
Classifier: Topic :: Software Development :: Libraries :: Python Modules
Classifier: Topic :: Software Development :: Localization
Classifier: License :: OSI Approved :: MIT License
Classifier: Programming Language :: Python :: 3.9
Requires-Python: >=3.9
License-File: LICENSE
